README.md
setup.cfg
setup.py
pj_distributions/Binomialdistribution.py
pj_distributions/Gaussiandistribution.py
pj_distributions/Generaldistribution.py
pj_distributions/__init__.py
pj_distributions.egg-info/PKG-INFO
pj_distributions.egg-info/SOURCES.txt
pj_distributions.egg-info/dependency_links.txt
pj_distributions.egg-info/not-zip-safe
pj_distributions.egg-info/top_level.txt